LICENSE
MANIFEST.in
README.md
setup.py
message_media_signing_keys/__init__.py
message_media_signing_keys/api_helper.py
message_media_signing_keys/configuration.py
message_media_signing_keys/decorators.py
message_media_signing_keys/message_media_signing_keys_client.py
message_media_signing_keys/controllers/__init__.py
message_media_signing_keys/controllers/base_controller.py
message_media_signing_keys/controllers/signature_key_management_controller.py
message_media_signing_keys/exceptions/__init__.py
message_media_signing_keys/exceptions/api_exception.py
message_media_signing_keys/exceptions/create_signature_key_400_response_exception.py
message_media_signing_keys/exceptions/create_signature_key_403_response_exception.py
message_media_signing_keys/exceptions/delete_signature_key_403_response_exception.py
message_media_signing_keys/exceptions/disable_the_current_enabled_signature_key_403_response_exception.py
message_media_signing_keys/exceptions/enable_signature_key_400_response_exception.py
message_media_signing_keys/exceptions/enable_signature_key_403_response_exception.py
message_media_signing_keys/exceptions/get_enabled_signature_key_403_response_exception.py
message_media_signing_keys/exceptions/get_signature_key_detail_400_response_exception.py
message_media_signing_keys/exceptions/get_signature_key_detail_403_response_exception.py
message_media_signing_keys/exceptions/get_signature_key_list_400_response_exception.py
message_media_signing_keys/exceptions/get_signature_key_list_403_response_exception.py
message_media_signing_keys/http/__init__.py
message_media_signing_keys/http/http_call_back.py
message_media_signing_keys/http/http_client.py
message_media_signing_keys/http/http_context.py
message_media_signing_keys/http/http_method_enum.py
message_media_signing_keys/http/http_request.py
message_media_signing_keys/http/http_response.py
message_media_signing_keys/http/requests_client.py
message_media_signing_keys/http/auth/__init__.py
messagemedia_signingkeys_sdk.egg-info/PKG-INFO
messagemedia_signingkeys_sdk.egg-info/SOURCES.txt
messagemedia_signingkeys_sdk.egg-info/dependency_links.txt
messagemedia_signingkeys_sdk.egg-info/requires.txt
messagemedia_signingkeys_sdk.egg-info/top_level.txt
