Metadata-Version: 1.0
Name: messagemedia-signingkeys-sdk
Version: 1.1.0
Summary: The MessageMedia Signature Key API provides a number of endpoints  for managing key used to sign each unique request to ensure security  and the requests can't (easily) be spoofed. This is similar to using  HMAC in your outbound messaging (rather than HTTP Basic).
Home-page: https://developers.messagemedia.com
Author: MessageMedia Developers
Author-email: developers@messagemedia.com
License: UNKNOWN
Platform: UNKNOWN
